LICENSE
MANIFEST.in
README.md
setup.py
examples/__init__.py
examples/basic_usage.py
examples/test.py
wolai/__init__.py
wolai/client.py
wolai/models.py
wolai.egg-info/PKG-INFO
wolai.egg-info/SOURCES.txt
wolai.egg-info/dependency_links.txt
wolai.egg-info/requires.txt
wolai.egg-info/top_level.txt